libtado/__init__.py
libtado/__main__.py
libtado/api.py
libtado/cli_utils.py
libtado-4.1.1.dist-info/METADATA
libtado-4.1.1.dist-info/WHEEL
libtado-4.1.1.dist-info/entry_points.txt
libtado-4.1.1.dist-info/licenses/LICENSE
libtado-4.1.1.dist-info/RECORD
