Metadata-Version: 2.4
Name: libtado
Version: 4.1.1
Summary: A library (and a command line client) to control your Tado Smart Thermostat.
License: GNU GPL v3.0
License-File: LICENSE
Author: Germain Lefebvre
Author-email: germain.lefebvre4@gmail.com
Requires-Python: >=3.8.1,<4.0
Classifier: License :: OSI Approved :: GNU General Public License v3 or later (GPLv3+)
Classifier: License :: Other/Proprietary License
Classifier: Operating System :: OS Independent
Classifier: Programming Language :: Python :: 3
Classifier: Programming Language :: Python :: 3.9
Classifier: Programming Language :: Python :: 3.10
Classifier: Programming Language :: Python :: 3.11
Classifier: Programming Language :: Python :: 3.12
Classifier: Programming Language :: Python :: 3.13
Classifier: Programming Language :: Python :: 3.14
Requires-Dist: click
Requires-Dist: python-dateutil
Requires-Dist: requests
Project-URL: Documentation, https://libtado.readthedocs.io/
Project-URL: Homepage, https://libtado.readthedocs.io/
Project-URL: Repository, https://github.com/germainlefebvre4/libtado
